{"Rank":"1","Name":"BTCBitcoin","Symbol":"BTC","Market Cap":"$5,770,476,777.82","Price":"$382.30","Circulating Supply":"15,094,150 BTC","volume (24h)":"$45,319,584.00","% 1h":"-1.20%","% 24h":"-1.18%","% 7d":"-14.59%","":""}
{"Rank":"2","Name":"XRPXRP","Symbol":"XRP","Market Cap":"$176,601,304.50","Price":"$0.005266","Circulating Supply":"33,537,439,933 XRP","volume (24h)":"$473,174.75","% 1h":"-0.27%","% 24h":"2.92%","% 7d":"-11.58%","":""}
{"Rank":"3","Name":"LTCLitecoin","Symbol":"LTC","Market Cap":"$133,438,085.99","Price":"$3.0262","Circulating Supply":"44,094,382 LTC","volume (24h)":"$1,905,659.63","% 1h":"-0.78%","% 24h":"-1.68%","% 7d":"-14.34%","":""}
{"Rank":"4","Name":"ETHEthereum","Symbol":"ETH","Market Cap":"$101,329,062.02","Price":"$1.3275","Circulating Supply":"76,332,670 ETH","volume (24h)":"$1,171,146.00","% 1h":"2.05%","% 24h":"8.31%","% 7d":"30.49%","":""}
{"Rank":"5","Name":"DASHDash","Symbol":"DASH","Market Cap":"$30,466,572.18","Price":"$4.9535","Circulating Supply":"6,150,529 DASH","volume (24h)":"$560,892.13","% 1h":"5.33%","% 24h":"24.39%","% 7d":"54.65%","":""}
{"Rank":"6","Name":"DOGEDogecoin","Symbol":"DOGE","Market Cap":"$15,626,952.07","Price":"$0.0001522","Circulating Supply":"102,705,607,764 DOGE","volume (24h)":"$64,727.93","% 1h":"0.31%","% 24h":"-1.78%","% 7d":"-10.15%","":""}
{"Rank":"7","Name":"PPCPeercoin","Symbol":"PPC","Market Cap":"$9,427,550.46","Price":"$0.4113","Circulating Supply":"22,921,429 PPC","volume (24h)":"$33,443.82","% 1h":"-0.71%","% 24h":"2.06%","% 7d":"-0.99%","":""}
{"Rank":"8","Name":"FCTFactom","Symbol":"FCT","Market Cap":"$8,472,205.53","Price":"$0.9678","Circulating Supply":"8,753,819 FCT","volume (24h)":"$240,137.53","% 1h":"0.51%","% 24h":"7.81%","% 7d":"35.69%","":""}
{"Rank":"9","Name":"XLMStellar","Symbol":"XLM","Market Cap":"$8,293,148.47","Price":"$0.001714","Circulating Supply":"4,837,356,606 XLM","volume (24h)":"$25,329.37","% 1h":"-0.90%","% 24h":"-0.94%","% 7d":"-2.79%","":""}
{"Rank":"10","Name":"EMCEmercoin","Symbol":"EMC","Market Cap":"$7,754,919.94","Price":"$0.21","Circulating Supply":"36,933,113 EMC","volume (24h)":"$18,179.03","% 1h":"-1.78%","% 24h":"-16.65%","% 7d":"36.55%","":""}
{"Rank":"11","Name":"BTSBitShares","Symbol":"BTS","Market Cap":"$7,708,844.07","Price":"$0.003037","Circulating Supply":"2,538,465,674 BTS","volume (24h)":"$93,170.79","% 1h":"-0.13%","% 24h":"-0.86%","% 7d":"<0.01%","":""}
{"Rank":"12","Name":"NXTNxt","Symbol":"NXT","Market Cap":"$6,990,852.95","Price":"$0.006991","Circulating Supply":"999,997,096 NXT","volume (24h)":"$19,670.29","% 1h":"-0.57%","% 24h":"-2.11%","% 7d":"8.21%","":""}
{"Rank":"13","Name":"MAIDMaidSafeCoin","Symbol":"MAID","Market Cap":"$6,744,058.83","Price":"$0.0149","Circulating Supply":"452,552,412 MAID","volume (24h)":"$3,952.03","% 1h":"-3.54%","% 24h":"-2.07%","% 7d":"-13.38%","":""}
{"Rank":"14","Name":"BCNBytecoin","Symbol":"BCN","Market Cap":"$6,020,015.82","Price":"$0.00003372","Circulating Supply":"178,549,893,755 BCN","volume (24h)":"$4,011.71","% 1h":"-1.59%","% 24h":"-3.31%","% 7d":"1.34%","":""}
{"Rank":"15","Name":"YBCYbCoin","Symbol":"YBC","Market Cap":"$5,900,571.18","Price":"$1.9626","Circulating Supply":"3,006,578 YBC","volume (24h)":"$1,103,769.00","% 1h":"0.43%","% 24h":"12.64%","% 7d":"150.49%","":""}
{"Rank":"16","Name":"NMCNamecoin","Symbol":"NMC","Market Cap":"$5,261,458.29","Price":"$0.3927","Circulating Supply":"13,397,700 NMC","volume (24h)":"$9,339.52","% 1h":"-1.27%","% 24h":"-2.04%","% 7d":"-7.72%","":""}
{"Rank":"17","Name":"XMRMonero","Symbol":"XMR","Market Cap":"$4,837,867.18","Price":"$0.4508","Circulating Supply":"10,732,359 XMR","volume (24h)":"$61,135.99","% 1h":"0.50%","% 24h":"-8.42%","% 7d":"-7.59%","":""}
{"Rank":"18","Name":"GRCGridCoin","Symbol":"GRC","Market Cap":"$2,858,739.58","Price":"$0.007683","Circulating Supply":"372,109,484 GRC","volume (24h)":"$759.17","% 1h":"-0.08%","% 24h":"10.02%","% 7d":"-8.19%","":""}
