{"Rank":"1","Name":"BTCBitcoin","Symbol":"BTC","Market Cap":"$803,744,511,638.35","Price":"$42,412.43","Circulating Supply":"18,950,681 BTC","volume (24h)":"$16,142,097,333.90","% 1h":"1.92%","% 24h":"2.34%","% 7d":"11.85%","":""}
{"Rank":"2","Name":"ETHEthereum","Symbol":"ETH","Market Cap":"$365,288,302,066.81","Price":"$3,057.48","Circulating Supply":"119,473,804 ETH","volume (24h)":"$9,466,018,022.46","% 1h":"2.19%","% 24h":"1.42%","% 7d":"17.44%","":""}
{"Rank":"3","Name":"USDTTether","Symbol":"USDT","Market Cap":"$77,961,684,799.00","Price":"$1.0007","Circulating Supply":"77,908,751,039 USDT *","volume (24h)":"$40,572,292,703.17","% 1h":"0.02%","% 24h":"<0.01%","% 7d":"0.03%","":""}
{"Rank":"4","Name":"BNBBNB","Symbol":"BNB","Market Cap":"$69,274,003,460.63","Price":"$419.55","Circulating Supply":"165,116,761 BNB *","volume (24h)":"$1,427,593,920.56","% 1h":"1.92%","% 24h":"1.29%","% 7d":"11.10%","":""}
{"Rank":"5","Name":"USDCUSD Coin","Symbol":"USDC","Market Cap":"$51,054,224,335.10","Price":"$1.0004","Circulating Supply":"51,036,025,522 USDC *","volume (24h)":"$2,185,135,025.31","% 1h":"0.04%","% 24h":"0.02%","% 7d":"0.03%","":""}
{"Rank":"6","Name":"ADACardano","Symbol":"ADA","Market Cap":"$38,433,324,420.14","Price":"$1.1445","Circulating Supply":"33,579,503,408 ADA","volume (24h)":"$911,521,817.52","% 1h":"1.86%","% 24h":"1.53%","% 7d":"10.32%","":""}
{"Rank":"7","Name":"SOLSolana","Symbol":"SOL","Market Cap":"$36,532,195,892.09","Price":"$115.30","Circulating Supply":"316,845,383 SOL *","volume (24h)":"$1,488,437,091.46","% 1h":"2.32%","% 24h":"1.23%","% 7d":"23.58%","":""}
{"Rank":"8","Name":"XRPXRP","Symbol":"XRP","Market Cap":"$32,700,536,071.05","Price":"$0.6836","Circulating Supply":"47,832,461,678 XRP *","volume (24h)":"$1,095,140,341.04","% 1h":"1.77%","% 24h":"2.48%","% 7d":"13.34%","":""}
{"Rank":"9","Name":"LUNATerra","Symbol":"LUNA","Market Cap":"$22,492,358,593.97","Price":"$56.10","Circulating Supply":"400,917,013 LUNA *","volume (24h)":"$1,300,455,897.56","% 1h":"3.64%","% 24h":"1.31%","% 7d":"21.24%","":""}
{"Rank":"10","Name":"DOTPolkadot","Symbol":"DOT","Market Cap":"$21,631,280,299.89","Price":"$21.90","Circulating Supply":"987,579,315 DOT *","volume (24h)":"$830,919,540.24","% 1h":"3.45%","% 24h":"2.51%","% 7d":"20.53%","":""}
{"Rank":"11","Name":"DOGEDogecoin","Symbol":"DOGE","Market Cap":"$20,400,845,319.46","Price":"$0.1538","Circulating Supply":"132,670,764,300 DOGE","volume (24h)":"$757,004,142.23","% 1h":"1.43%","% 24h":"4.51%","% 7d":"10.25%","":""}
{"Rank":"12","Name":"AVAXAvalanche","Symbol":"AVAX","Market Cap":"$19,306,314,558.70","Price":"$78.76","Circulating Supply":"245,136,941 AVAX *","volume (24h)":"$506,746,737.76","% 1h":"3.92%","% 24h":"1.95%","% 7d":"15.86%","":""}
{"Rank":"13","Name":"BUSDBinance USD","Symbol":"BUSD","Market Cap":"$16,520,648,299.56","Price":"$0.9999","Circulating Supply":"16,522,327,497 BUSD *","volume (24h)":"$3,226,430,907.02","% 1h":"<0.01%","% 24h":"0.11%","% 7d":"-0.11%","":""}
{"Rank":"14","Name":"SHIBShiba Inu","Symbol":"SHIB","Market Cap":"$15,596,217,120.71","Price":"$0.00002841","Circulating Supply":"549,063,278,876,302 SHIB *","volume (24h)":"$2,156,462,842.14","% 1h":"4.38%","% 24h":"26.16%","% 7d":"34.66%","":""}
{"Rank":"15","Name":"MATICPolygon","Symbol":"MATIC","Market Cap":"$12,981,893,615.00","Price":"$1.7400","Circulating Supply":"7,461,070,291 MATIC *","volume (24h)":"$692,969,600.36","% 1h":"2.60%","% 24h":"1.49%","% 7d":"8.39%","":""}
{"Rank":"16","Name":"CROCrypto.com Coin","Symbol":"CRO","Market Cap":"$11,661,744,341.53","Price":"$0.4616","Circulating Supply":"25,263,013,692 CRO *","volume (24h)":"$110,825,544.56","% 1h":"2.47%","% 24h":"2.91%","% 7d":"8.84%","":""}
{"Rank":"17","Name":"USTTerraUSD","Symbol":"UST","Market Cap":"$11,299,508,167.99","Price":"$1.0022","Circulating Supply":"11,274,253,969 UST *","volume (24h)":"$167,274,345.46","% 1h":"0.15%","% 24h":"0.05%","% 7d":"0.25%","":""}
{"Rank":"18","Name":"WBTCWrapped Bitcoin","Symbol":"WBTC","Market Cap":"$11,067,758,773.96","Price":"$42,249.07","Circulating Supply":"261,965 WBTC *","volume (24h)":"$163,994,478.11","% 1h":"1.56%","% 24h":"1.88%","% 7d":"11.29%","":""}
