{"Rank":"1","Name":"BTCBitcoin","Symbol":"BTC","Market Cap":"$517,116,820,259.63","Price":"$26,534.19","Circulating Supply":"19,488,700 BTC","volume (24h)":"$6,774,210,669.73","% 1h":"0.22%","% 24h":"-0.13%","% 7d":"2.72%","":""}
{"Rank":"2","Name":"ETHEthereum","Symbol":"ETH","Market Cap":"$195,111,799,251.34","Price":"$1,622.90","Circulating Supply":"120,224,407 ETH *","volume (24h)":"$3,032,716,258.02","% 1h":"0.19%","% 24h":"-0.75%","% 7d":"0.38%","":""}
{"Rank":"3","Name":"USDTTether USDt","Symbol":"USDT","Market Cap":"$83,066,181,171.94","Price":"$1.0003","Circulating Supply":"83,041,923,536 USDT *","volume (24h)":"$12,731,066,338.00","% 1h":"-0.02%","% 24h":"0.00%","% 7d":"0.07%","":""}
{"Rank":"4","Name":"BNBBNB","Symbol":"BNB","Market Cap":"$33,302,871,729.66","Price":"$216.47","Circulating Supply":"153,848,214 BNB *","volume (24h)":"$432,102,185.59","% 1h":"0.07%","% 24h":"0.70%","% 7d":"1.95%","":""}
{"Rank":"5","Name":"XRPXRP","Symbol":"XRP","Market Cap":"$26,217,650,533.39","Price":"$0.493","Circulating Supply":"53,175,400,720 XRP *","volume (24h)":"$500,486,647.85","% 1h":"0.09%","% 24h":"-1.37%","% 7d":"-0.96%","":""}
{"Rank":"6","Name":"USDCUSD Coin","Symbol":"USDC","Market Cap":"$26,168,221,491.30","Price":"$1.0001","Circulating Supply":"26,166,039,484 USDC *","volume (24h)":"$1,585,056,980.59","% 1h":"-0.01%","% 24h":"-0.01%","% 7d":"0.01%","":""}
{"Rank":"7","Name":"DOGEDogecoin","Symbol":"DOGE","Market Cap":"$8,676,940,749.20","Price":"$0.06152","Circulating Supply":"141,049,666,384 DOGE","volume (24h)":"$156,292,597.17","% 1h":"0.10%","% 24h":"-1.02%","% 7d":"0.31%","":""}
{"Rank":"8","Name":"ADACardano","Symbol":"ADA","Market Cap":"$8,682,830,662.83","Price":"$0.2473","Circulating Supply":"35,108,275,727 ADA *","volume (24h)":"$85,817,848.21","% 1h":"0.25%","% 24h":"-1.25%","% 7d":"-0.70%","":""}
{"Rank":"9","Name":"TONToncoin","Symbol":"TON","Market Cap":"$7,950,782,673.16","Price":"$2.3167","Circulating Supply":"3,431,892,088 TON *","volume (24h)":"$50,336,185.95","% 1h":"1.18%","% 24h":"-3.21%","% 7d":"34.70%","":""}
{"Rank":"10","Name":"SOLSolana","Symbol":"SOL","Market Cap":"$7,747,279,411.94","Price":"$18.83","Circulating Supply":"411,397,197 SOL *","volume (24h)":"$112,594,680.34","% 1h":"0.29%","% 24h":"-1.61%","% 7d":"3.19%","":""}
{"Rank":"11","Name":"TRXTRON","Symbol":"TRX","Market Cap":"$7,436,134,568.09","Price":"$0.08338","Circulating Supply":"89,183,580,891 TRX *","volume (24h)":"$131,356,021.93","% 1h":"-0.04%","% 24h":"-0.17%","% 7d":"6.45%","":""}
{"Rank":"12","Name":"DAIDai","Symbol":"DAI","Market Cap":"$5,350,410,755.80","Price":"$1.0005","Circulating Supply":"5,347,888,596 DAI *","volume (24h)":"$52,246,843.52","% 1h":"0.03%","% 24h":"0.04%","% 7d":"0.11%","":""}
{"Rank":"13","Name":"DOTPolkadot","Symbol":"DOT","Market Cap":"$4,989,232,833.23","Price":"$4.0746","Circulating Supply":"1,224,472,277 DOT *","volume (24h)":"$69,631,308.58","% 1h":"0.14%","% 24h":"-2.65%","% 7d":"-1.86%","":""}
{"Rank":"14","Name":"MATICPolygon","Symbol":"MATIC","Market Cap":"$4,822,564,221.56","Price":"$0.5175","Circulating Supply":"9,319,469,069 MATIC *","volume (24h)":"$174,765,548.79","% 1h":"0.18%","% 24h":"-2.13%","% 7d":"-1.15%","":""}
{"Rank":"15","Name":"LTCLitecoin","Symbol":"LTC","Market Cap":"$4,683,473,115.37","Price":"$63.58","Circulating Supply":"73,664,733 LTC","volume (24h)":"$238,602,170.34","% 1h":"0.25%","% 24h":"-2.70%","% 7d":"4.02%","":""}
{"Rank":"16","Name":"WBTCWrapped Bitcoin","Symbol":"WBTC","Market Cap":"$4,316,919,546.00","Price":"$26,488.27","Circulating Supply":"162,975 WBTC *","volume (24h)":"$97,428,504.70","% 1h":"0.09%","% 24h":"-0.27%","% 7d":"2.45%","":""}
{"Rank":"17","Name":"SHIBShiba Inu","Symbol":"SHIB","Market Cap":"$4,250,727,271.71","Price":"$0.00000721","Circulating Supply":"589,346,914,631,298 SHIB *","volume (24h)":"$70,966,086.72","% 1h":"0.77%","% 24h":"-2.51%","% 7d":"-2.12%","":""}
{"Rank":"18","Name":"BCHBitcoin Cash","Symbol":"BCH","Market Cap":"$4,091,877,662.39","Price":"$209.76","Circulating Supply":"19,507,113 BCH","volume (24h)":"$157,999,941.50","% 1h":"0.35%","% 24h":"-2.51%","% 7d":"10.07%","":""}
